Workbook

Sheet Loan Tape
B2: Loan ID | C2: City | D2: Status | E2: Remarks | F2: Category | G2: Earmarked | H2: Current Facility | I2: Initial Facility | J2: Commitment | K2: Outstanding | L2: Undrawn | M2: Interest Rate | N2: RED IV Start Date | O2: Original Start Date | P2: Maturity Date | Q2: Rental Income | R2: Valuation (as-is) | S2: Valuation date | T2: LTV | U2: Duration | V2: Google Maps | W2: kadastralekaart | X2: Photo | Y2: Additional Information
B3: 484 | C3: Utrecht | D3: Redevelopment | E3: Construction financing of a former office asset into hotel and short-stay apartments. Fully permitted | F3: Hotel | G3: FALSE | H3: RED IV | I3: TLFOKT25 | J3: 25000000 | K3: 8696509.1 | L3: 16303491 | M3: 0.08 | N3: 45658 | O3: 45992 | P3: 46692 | Q3: 0 | R3: 39300000 | S3: 45741 | T3: 0.63613232 | U3: 1.9164956 | V3: https://maps.app.goo.gl/x385UQeZKvp2qAGQ6 | W3: https://kadastralekaart.com/kaart/perceel/LWR01/B/5681 | X3: https://i.imgur.com/CeR2Uvu.png | Y3: This financing concerns the redevelopment of an office property in Utrecht into a hotel and short-stay apartments. The asset is a former office building for which permits have been obtained to create roughly 40 hotel rooms and around 90 short-stay units, supported by a fixed-price construction contract and a signed operating agreement with an established local operator. The acquisition was previously financed under an earlier vehicle (RED III), which will be refinanced through this construction loan. The risk-bearing capital amounts to roughly 30 percent of the total investment. Construction risks are mitigated through third-party supervision and a cost-overrun guarantee. Operational risk relates mainly to the short-stay component but is supported by conservative assumptions and strong operator performance. Given the acceptable leverage metrics, solid location and clear value-creation strategy, this is considered an appropriate financing for RED IV.
B4: 493 | C4: Baarn | D4: Leased | E4: Owner-occupied asset. Borrower is a portco of a large PE firm | F4: Light Industrial | G4: TRUE | H4: RED IV | I4: TLFSEP25 | J4: 7500000 | K4: 7500000 | L4: 0 | M4: 0.08 | N4: 45658 | O4: 45962 | P4: 47027 | Q4: 900000 | R4: 12250000 | S4: 45839 | T4: 0.6122449 | U4: 2.9158111 | V4: https://maps.app.goo.gl/oSoxvhLHxdShkkwy6 | W4: https://kadastralekaart.com/kaart/perceel/BAA01/H/2736 | X4: https://i.imgur.com/FcQ7Res.png | Y4: Financing of a light-industrial warehouse in Baarn, near the A1-highway. Consists of 15.358m2 LFA (plot size 15.425m2). The property is in good condition and leased (owner-user) for €900.000 per annum; €59/m2 LFA. ICR 1,22 (based on a net income of €730.000 per annum). LTV (61%) is good, but to further guarantee a solid financing position we arranged a €1.000.000 guarantee from the sponsor. Overall, the transaction presents a well-structured and balanced financing facility with appropriate downside protection and a clear exit-optionality. Loan metrics are good. Overall, this is a responsible loan for RED IV.
B5: 504 | C5: Den Bosch | D5: Leased | E5: Prime retail property with strong tenant (HEMA) | F5: Retail | G5: TRUE | H5: RED IV | I5: TLFOKT25 | J5: 7000000 | K5: 7000000 | L5: 0 | M5: 0.08 | N5: 45658 | O5: 45962 | P5: 47041 | Q5: 780100 | R5: 10670000 | S5: 45859 | T5: 0.65604499 | U5: 2.954141 | V5: https://maps.app.goo.gl/jZDJQvR6hmf9TUFt9 | W5: https://kadastralekaart.com/kaart/perceel/HTG00/G/6916 | X5: https://i.imgur.com/0aZbpAD.png | Y5: Acquisition financing of an A1-retail asset in Den Bosch (approx. 4.200m2 LFA divided over 5 layers). Borrower bought the property, in a share-transaction, for approx. €10.670.000. We finance €7.000.000 (65% LTV). The property’s location is good. The property is leased to HEMA for €780.000 per annum. Recently, an extension of the lease contract has been signed. The new end-date is 01-11-2035, hence limiting vacancy risk during the loan period. The borrower is an experienced entrepreneur and real estate investor. The borrower personally guarantees for this loan. Loan metrics are good. Overall, this is a responsible loan for RED IV.
B6: 505 | C6: Den Dolder | D6: Redevelopment | E6: Purchase of monumental land estate for redevelopment | F6: Residential | G6: FALSE | H6: RED IV | I6: TLFSEP25 | J6: 2500000 | K6: 2500000 | L6: 0 | M6: 0.0875 | N6: 45658 | O6: 45931 | P6: 46275 | Q6: 0 | R6: 3800000 | S6: 45901 | T6: 0.65789474 | U6: 0.94182067 | V6: https://maps.app.goo.gl/XgedgBv4umzfGicT9 | W6: https://kadastralekaart.com/kaart/perceel/ZEI00/A/4001 | X6: https://i.imgur.com/sf08rQy.png | Y6: Financing of the acquisition of an estate in Den Dolder. Purchase price €3.800.000. This concerns the financing of a country estate consisting of a complex of buildings, a.o. a residual building, office wings, situated on a generous plot of 54,110 m². The total gross floor area amounts to 1,563 m². The estate has NSW-status, which provides favourable tax treatment (no transfer tax). The property is in good condition. Borrower intends to redevelop the estate, converting the office wing and the main residence into residential units: • 10 affordable maisonette homes in the office wing (priced up to NHG cap / max. €450,000) – GO 574 m² • 2 penthouses in former main residence – GO 260 m² • 2 apartments in former main residence – GO 170 m² • Main villa – GO 462 m² • Garden/groundskeeper’s house – approx. 100 m² Loan metrics are strong. Even in the current as-is situation, the loan-to-cost level is responsible at 66% LTC, and the borrower provides a personal guarantee. Overall, this represents a responsible financing for RED IV.
B7: 507 | C7: Ridderkerk | D7: Leased | E7: Existing shopping center on ground floor; Refurbishment of vacant upper floors into care apartments | F7: Retail | G7: TRUE | H7: RED IV | I7: TLFOKT25 | J7: 6500000 | K7: 4693871.8 | L7: =J7-K7 -> 1806128.2 | M7: 0.0865 | N7: 45658 | O7: 45962 | P7: 46478 | Q7: 1369000 | R7: 20460000 | S7: 45820 | T7: 0.31769306 | U7: 1.412731 | V7: https://maps.app.goo.gl/8vhTyidXzgWG7xhE7 | W7: https://kadastralekaart.com/kaart/perceel/RDK01/H/6686 | X7: https://i.imgur.com/yuPTY3y.png | Y7: Property, shopping centre, consists of 21 retail units and an underground Q-Park garage (140 spaces). Annual rental income €724.000 (excl. €170.000 service charges), WAULT 8.6 years, with HEMA as anchor tenant. Borrower will convert the former (vacant) library on the first floor into 38 healthcare-residential units (1.180 m²). Permit is irrevocable and all units are pre-leased to one healthcare operator (contract signed). We finance the construction, but we hold the first mortgage right over the entire asset. Low leverage: 32% LTV. Borrower is a reputable and experienced real estate developer. Conclusion: Low-risk loan backed by leased-retail cash flow and a secured, pre-leased healthcare redevelopment.
B8: 509 | C8: Rotterdam | D8: Leased | E8: Leased asset to a medical centre. Possible future redevelopment | F8: Mixed | G8: TRUE | H8: RED IV | I8: TLFOKT25 | J8: 1500000 | K8: 1500000 | L8: 0 | M8: 0.0775 | N8: 45658 | O8: 45962 | P8: 46486 | Q8: 160000 | R8: 2200000 | S8: 45505 | T8: 0.68181818 | U8: 1.4346338 | V8: https://maps.app.goo.gl/FptBuZHcGyUDT5H86 | W8: https://kadastralekaart.com/kaart/perceel/RTD05/Q/4075 | X8: https://i.imgur.com/QE6pVzd.png | Y8: Financing of an office building (leasehold) in Rotterdam – Kop van Zuid. Borrower acquired the asset in 2024 for €2.250.000 (approx. 66% LTC). The property comprises 1.646 m² GFA (incl. 313 m² basement) and 900 m² usable area, across a basement, ground floor, two upper floors and an attic, on a 945 m² plot. The building is fully leased to a large physiotherapy practice for ~€160,000 p.a.. Lease runs until Oct-2031. The property has redevelopment potential. Borrower is progressing a hotel redevelopment plan and permit application, aligned with the municipal area vision. Zoning (“Gemengd – 3”) allows residential, office, commercial, social and hotel/hospitality uses. We finance on the as-is value. Location and future potential enhance marketability. Rental income covers interest (ICR ~1.09) and borrower provides a personal guarantee. Overall, a low-risk financing with secure cash flow, solid collateral and (future) upside from redevelopment. Exit expected via refinancing upon permit approval.
B9: 510 | C9: Muiden | D9: Development | E9: Top-up construction facility for completion of apartment complex | F9: Residential | G9: FALSE | H9: RED IV | I9: TLFOKT25 | J9: 2700000 | K9: 2700000 | L9: 0 | M9: 0.09 | N9: 45658 | O9: 45931 | P9: 46387 | Q9: 0 | R9: 8000000 | S9: 45931 | T9: 0.3375 | U9: 1.24846 | V9: https://maps.app.goo.gl/ZC6GoESnvdcv5QAb9 | W9: https://kadastralekaart.com/kaart/perceel/MDN01/B/2682 | X9: https://i.imgur.com/LkntWiX.png | Y9: Fnancing of the construction of phase 3 of this resi-project (“De Werf bij de Sluis in Muiden”). The construction of phase 2 is almost finished. The project consists of high-end apartments located at the Vecht-river, including a sports-harbour. The borrower is a well-capitalized and professional party with a good track-record in developing. The security comes from the underlying value of the assets which is partly the land position of Phase 3 and the unsold apartments of phase 2. Loan metrics are good. Overall, this is a responsible loan for RED IV.
B10: 511 | C10: Amsterdam | D10: Leased | E10: Short term Bridge finance of leased resi units in Amsterdam | F10: Residential | G10: TRUE | H10: RED IV | I10: TLFNOV25A | J10: 2500000 | K10: 2500000 | L10: 0 | M10: 0.08 | N10: 45658 | O10: 45962 | P10: 46142 | Q10: 124000 | R10: 5138480 | S10: 45931 | T10: 0.4865252 | U10: 0.49281314 | Y10: The company requires temporary liquidity to bridge the period until completion of an ongoing refinancing process with a major bank. Several unencumbered assets are available as collateral, mainly residential units (split apartments) in Amsterdam, generating approximately €124,000 gross per year, complemented by three owner-occupied commercial properties. The total portfolio value, including these assets, amounts to roughly €5.44 million, resulting in an LTV between 46–57%. The facility is provided at a conservative level considering the underlying value of the collateral. The vacant value of the residential assets is significantly higher than the current low rental levels. The portfolio consists of 18 apartments in Amsterdam, two commercial properties in the Western Docklands, two industrial sites in Emmeloord, one apartment in Hilversum, and a recently acquired residential property in Hilversum valued at €1.5 million and situated on 7,100 m² of land. The average loan amount per asset, excluding the Hilversum residence, is around €108,000, with an estimated average value of €235,000. This reflects a prudent financing level given the liquidity and quality of the assets, of which approximately 75% are Amsterdam apartments. The borrower is financially solid with sufficient cash flow and a long-standing profitable track record. Assets are well-located and easily marketable. The operator has extensive experience in real estate and provides personal recourse. Exit will occur through refinancing once the bank facility is completed. Overall, a suitable proposition for RED IV.
B11: 513 | C11: Den Bosch | D11: Leased | E11: Leased, office asset - multi tenants | F11: Office | G11: TRUE | H11: RED IV | I11: TLFDECC | J11: 8250000 | K11: 8250000 | L11: 0 | M11: 0.0715 | N11: 45658 | O11: 46023 | P11: 47105 | Q11: 1230000 | R11: 13800000 | S11: 45951 | T11: 0.59782609 | U11: 2.9623546 | V11: https://maps.app.goo.gl/bs2Ne8cMyrQArArX7 | W11: https://kadastralekaart.com/kaart/perceel/HTG00/S/478 | X11: https://i.imgur.com/Re0YyXC.png | Y11: This financing concerns the acquisition of a fully leased office property in ’s-Hertogenbosch. The asset consists of three connected towers with a flexible layout, allowing for separation into individual units, and provides approximately 6,300m² LFA with ample parking. The property is modern, recently renovated, energy efficient and generates stable rental income.The WALT of 4.97 years strengthens the income profile, while a €1 million cash-sweep mechanism further mitigates risk by directly linking our exposure to rental performance. Exit risk is limited; supported by strong occupancy (WALT) and a long-term redevelopment potential into healthcare housing as a future upside alternative. While such redevelopment would require substantial work and time — zoning changes and permits — it provides an attractive optionality. Even if redevelopment proves challenging, the property in its current state remains a well-lettable investment product with solid saleability, particularly at the applied financing level.
B12: 514 | C12: Amsterdam | D12: Leased | E12: Resi asset with plan to split into smaller units and sale | F12: Residential | G12: FALSE | H12: RED IV | I12: TLFNOV25B | J12: 700000 | K12: 700000 | L12: 0 | M12: 0.0825 | N12: 45658 | O12: 45962 | P12: 46507 | Q12: 47000 | R12: 960000 | S12: 45902 | T12: 0.72916667 | U12: 1.4921287 | V12: https://maps.app.goo.gl/hAtL4DG9LciUpMXdA | W12: https://kadastralekaart.com/kaart/perceel/ASD07/K/8669 | X12: https://i.imgur.com/KmOoASF.jpeg | Y12: This financing concerns the acquisition of a leased residential property in Amsterdam-Noord (leasehold) consisting of three units with a total GFA of roughly 250–275m². The borrower intends to vacate the units, legally subdivide the property and either sell the apartments individually or renovate further depending on market conditions. The valuation supports the business plan, with current value around €960.000 and exit potential of €1.500.000–€1.650.000. Key risks relate to liquidity pressure and timing of subdivision, mitigated by an 18-month interest reserve and personal guarantees. Overall, the loan amount is considered acceptable given the vacant-possession potential and marketability.
B13: 515 | C13: Utrecht | D13: Leased | E13: Multi tenant offices. Possible long term redevelopment potential | F13: Office | G13: TRUE | H13: RED IV | I13: RED III | J13: 12000000 | K13: 12000000 | L13: 0 | M13: 0.07 | N13: 45689 | O13: 46054 | P13: 47114 | Q13: 2150000 | R13: 20050000 | S13: 45231 | T13: 0.59850374 | U13: 2.9021218 | V13: https://maps.app.goo.gl/6aTGsroijrGwSurw7 | W13: https://kadastralekaart.com/kaart/perceel/UTT00/O/1117 | X13: https://i.imgur.com/xljbU1O.png | Y13: This proposal concerns the financing of multiple commercial objects located near the FC Utrecht stadium. In the near future, there are opportunities to redevelop the area, with the possibility to add residential units on top of the existing structures. Borrower wishes to bridge the term to obtain a permit for this redevelopment. Borrower is an SPV with two sponsors: a professional developer with proven track-record and a private investor with healthy financials. There is only limited recourse. Objects are well-maintained and well-rented to cover the interest expenses. WALT is acceptable given the maturity of this loan. LTV based on the as is situation and cash flow are sufficient. The loan is fits well within the terms of RED.
B14: 518 | C14: Amsterdam / Almere / Amersfoort | D14: Leased | E14: Portfolio of residential, commercial and office assets | F14: Mixed | G14: TRUE | H14: TLFJANA | I14: TLFJANA | J14: 5000000 | K14: 5000000 | L14: 0 | M14: 0.09 | O14: 46054 | P14: 46215 | Q14: 867000 | R14: 14580000 | S14: 46023 | T14: 0.34293553 | U14: 0.44079398 | V14: 0 | W14: 0 | X14: 0 | Y14: 0
B15: 520 | C15: Oss | D15: Leased | E15: Partially owner-occupied modern industrial property | F15: Light Industrial | G15: TRUE | H15: TLFDECA | I15: TLFDECA | J15: 8000000 | K15: 8000000 | L15: 0 | M15: 0.08 | N15: 45689 | O15: 46023 | P15: 47106 | Q15: 1500000 | R15: 23500000 | S15: 45953 | T15: 0.34042553 | U15: 2.9650924 | V15: https://maps.app.goo.gl/2Gw73caiUCVRvPNb6 | W15: https://kadastralekaart.com/kaart/perceel/OSS00/B/6494 | X15: https://i.imgur.com/6t0C7AB.png | Y15: This financing concerns a first-mortgage loan secured on a recently completed, modern industrial property located on a well-accessible business park near the motorway. The asset has an appraised value of approximately €23.5 million and is fully leased, generating around €1.5 million in annual rental income. The financing is provided at a conservative leverage level, with an LTV of roughly 34 percent, offering substantial downside protection. Rental income is diversified between an external logistics tenant under a long-term lease and an owner-occupier. Sponsor commitment is reinforced through significant subordinated capital remaining in the structure. Overall, the combination of strong asset quality, low leverage, stable income and clear exit options results in an attractive, well-secured financing aligned with the investment profile of RAX RED IV.
B16: 522 | C16: Zevenaar | D16: Development | E16: Fully permitted land for residential development | F16: Residential | G16: FALSE | H16: RED IV | I16: RED IV | J16: 3000000 | K16: 3000000 | L16: 0 | M16: 0.083 | O16: 46054 | P16: 46589 | Q16: 0 | R16: 10000000 | S16: 46023 | T16: 0.3 | U16: 1.4647502 | V16: 0 | W16: 0 | X16: 0 | Y16: 0
B17: 512 | C17: Amsterdam | J17: 975000 | M17: 0.09 | O17: 45959 | P17: 46324 | R17: 2250000 | S17: 45931
B18: 526 | J18: 4200000 | K18: 4200000 | M18: 0.096 | O18: 46070 | P18: 46251 | R18: 9500000 | S18: 46054
B19: 527 | C19: Vught | J19: 2500000 | K19: 2500000 | M19: 0.1 | O19: 46054 | P19: 46388 | R19: 4000000 | S19: 46054
B20: 14 | J20: 92150000 | K20: 73523626 | L20: 18626374 | M20: 0.079510309 | Q20: 9127100 | R20: 184708480 | T20: 0.49889426 | U20: 2.1636508

Sheet csv
A1: ='Loan Tape'!B2 -> Loan ID | B1: ='Loan Tape'!C2 -> City | C1: ='Loan Tape'!D2 -> Status | D1: ='Loan Tape'!E2 -> Remarks | E1: ='Loan Tape'!F2 -> Category | F1: ='Loan Tape'!G2 -> Earmarked | G1: Facility | H1: Total Commitment | I1: Outstanding Loan Amount | J1: Undrawn Amount | K1: ='Loan Tape'!M2 -> Interest Rate | L1: Start Date | M1: Maturity | N1: ='Loan Tape'!Q2 -> Rental Income | O1: ='Loan Tape'!R2 -> Valuation (as-is) | P1: ='Loan Tape'!T2 -> LTV | Q1: ='Loan Tape'!U2 -> Duration | R1: google_maps | S1: ='Loan Tape'!W2 -> kadastralekaart | T1: ='Loan Tape'!X2 -> Photo | U1: ='Loan Tape'!Y2 -> Additional Information
A2: ='Loan Tape'!B3 -> 484 | B2: ='Loan Tape'!C3 -> Utrecht | C2: ='Loan Tape'!D3 -> Redevelopment | D2: ='Loan Tape'!E3 -> Construction financing of a former office asset into hotel and short-stay apartments. Fully permitted | E2: ='Loan Tape'!F3 -> Hotel | F2: ='Loan Tape'!G3 -> FALSE | G2: ='Loan Tape'!H3 -> RED IV | H2: ='Loan Tape'!J3 -> 25000000 | I2: ='Loan Tape'!K3 -> 8696509.1 | J2: ='Loan Tape'!L3 -> 16303491 | K2: ='Loan Tape'!M3 -> 0.08 | L2: ='Loan Tape'!O3 -> 45992 | M2: ='Loan Tape'!P3 -> 46692 | N2: ='Loan Tape'!Q3 -> 0 | O2: ='Loan Tape'!R3 -> 39300000 | P2: ='Loan Tape'!T3 -> 0.63613232 | Q2: ='Loan Tape'!U3 -> 1.9164956 | R2: ='Loan Tape'!V3 -> https://maps.app.goo.gl/x385UQeZKvp2qAGQ6 | S2: ='Loan Tape'!W3 -> https://kadastralekaart.com/kaart/perceel/LWR01/B/5681 | T2: ='Loan Tape'!X3 -> https://i.imgur.com/CeR2Uvu.png | U2: ='Loan Tape'!Y3 -> This financing concerns the redevelopment of an office property in Utrecht into a hotel and short-stay apartments. The asset is a former office building for which permits have been obtained to create roughly 40 hotel rooms and around 90 short-stay units, supported by a fixed-price construction contract and a signed operating agreement with an established local operator. The acquisition was previously financed under an earlier vehicle (RED III), which will be refinanced through this construction loan. The risk-bearing capital amounts to roughly 30 percent of the total investment. Construction risks are mitigated through third-party supervision and a cost-overrun guarantee. Operational risk relates mainly to the short-stay component but is supported by conservative assumptions and strong operator performance. Given the acceptable leverage metrics, solid location and clear value-creation strategy, this is considered an appropriate financing for RED IV.
A3: ='Loan Tape'!B4 -> 493 | B3: ='Loan Tape'!C4 -> Baarn | C3: ='Loan Tape'!D4 -> Leased | D3: ='Loan Tape'!E4 -> Owner-occupied asset. Borrower is a portco of a large PE firm | E3: ='Loan Tape'!F4 -> Light Industrial | F3: ='Loan Tape'!G4 -> TRUE | G3: ='Loan Tape'!H4 -> RED IV | H3: ='Loan Tape'!J4 -> 7500000 | I3: ='Loan Tape'!K4 -> 7500000 | J3: ='Loan Tape'!L4 -> 0 | K3: ='Loan Tape'!M4 -> 0.08 | L3: ='Loan Tape'!O4 -> 45962 | M3: ='Loan Tape'!P4 -> 47027 | N3: ='Loan Tape'!Q4 -> 900000 | O3: ='Loan Tape'!R4 -> 12250000 | P3: ='Loan Tape'!T4 -> 0.6122449 | Q3: ='Loan Tape'!U4 -> 2.9158111 | R3: ='Loan Tape'!V4 -> https://maps.app.goo.gl/oSoxvhLHxdShkkwy6 | S3: ='Loan Tape'!W4 -> https://kadastralekaart.com/kaart/perceel/BAA01/H/2736 | T3: ='Loan Tape'!X4 -> https://i.imgur.com/FcQ7Res.png | U3: ='Loan Tape'!Y4 -> Financing of a light-industrial warehouse in Baarn, near the A1-highway. Consists of 15.358m2 LFA (plot size 15.425m2). The property is in good condition and leased (owner-user) for €900.000 per annum; €59/m2 LFA. ICR 1,22 (based on a net income of €730.000 per annum). LTV (61%) is good, but to further guarantee a solid financing position we arranged a €1.000.000 guarantee from the sponsor. Overall, the transaction presents a well-structured and balanced financing facility with appropriate downside protection and a clear exit-optionality. Loan metrics are good. Overall, this is a responsible loan for RED IV.
A4: ='Loan Tape'!B5 -> 504 | B4: ='Loan Tape'!C5 -> Den Bosch | C4: ='Loan Tape'!D5 -> Leased | D4: ='Loan Tape'!E5 -> Prime retail property with strong tenant (HEMA) | E4: ='Loan Tape'!F5 -> Retail | F4: ='Loan Tape'!G5 -> TRUE | G4: ='Loan Tape'!H5 -> RED IV | H4: ='Loan Tape'!J5 -> 7000000 | I4: ='Loan Tape'!K5 -> 7000000 | J4: ='Loan Tape'!L5 -> 0 | K4: ='Loan Tape'!M5 -> 0.08 | L4: ='Loan Tape'!O5 -> 45962 | M4: ='Loan Tape'!P5 -> 47041 | N4: ='Loan Tape'!Q5 -> 780100 | O4: ='Loan Tape'!R5 -> 10670000 | P4: ='Loan Tape'!T5 -> 0.65604499 | Q4: ='Loan Tape'!U5 -> 2.954141 | R4: ='Loan Tape'!V5 -> https://maps.app.goo.gl/jZDJQvR6hmf9TUFt9 | S4: ='Loan Tape'!W5 -> https://kadastralekaart.com/kaart/perceel/HTG00/G/6916 | T4: ='Loan Tape'!X5 -> https://i.imgur.com/0aZbpAD.png | U4: ='Loan Tape'!Y5 -> Acquisition financing of an A1-retail asset in Den Bosch (approx. 4.200m2 LFA divided over 5 layers). Borrower bought the property, in a share-transaction, for approx. €10.670.000. We finance €7.000.000 (65% LTV). The property’s location is good. The property is leased to HEMA for €780.000 per annum. Recently, an extension of the lease contract has been signed. The new end-date is 01-11-2035, hence limiting vacancy risk during the loan period. The borrower is an experienced entrepreneur and real estate investor. The borrower personally guarantees for this loan. Loan metrics are good. Overall, this is a responsible loan for RED IV.
A5: ='Loan Tape'!B6 -> 505 | B5: ='Loan Tape'!C6 -> Den Dolder | C5: ='Loan Tape'!D6 -> Redevelopment | D5: ='Loan Tape'!E6 -> Purchase of monumental land estate for redevelopment | E5: ='Loan Tape'!F6 -> Residential | F5: ='Loan Tape'!G6 -> FALSE | G5: ='Loan Tape'!H6 -> RED IV | H5: ='Loan Tape'!J6 -> 2500000 | I5: ='Loan Tape'!K6 -> 2500000 | J5: ='Loan Tape'!L6 -> 0 | K5: ='Loan Tape'!M6 -> 0.0875 | L5: ='Loan Tape'!O6 -> 45931 | M5: ='Loan Tape'!P6 -> 46275 | N5: ='Loan Tape'!Q6 -> 0 | O5: ='Loan Tape'!R6 -> 3800000 | P5: ='Loan Tape'!T6 -> 0.65789474 | Q5: ='Loan Tape'!U6 -> 0.94182067 | R5: ='Loan Tape'!V6 -> https://maps.app.goo.gl/XgedgBv4umzfGicT9 | S5: ='Loan Tape'!W6 -> https://kadastralekaart.com/kaart/perceel/ZEI00/A/4001 | T5: ='Loan Tape'!X6 -> https://i.imgur.com/sf08rQy.png | U5: ='Loan Tape'!Y6 -> Financing of the acquisition of an estate in Den Dolder. Purchase price €3.800.000. This concerns the financing of a country estate consisting of a complex of buildings, a.o. a residual building, office wings, situated on a generous plot of 54,110 m². The total gross floor area amounts to 1,563 m². The estate has NSW-status, which provides favourable tax treatment (no transfer tax). The property is in good condition. Borrower intends to redevelop the estate, converting the office wing and the main residence into residential units: • 10 affordable maisonette homes in the office wing (priced up to NHG cap / max. €450,000) – GO 574 m² • 2 penthouses in former main residence – GO 260 m² • 2 apartments in former main residence – GO 170 m² • Main villa – GO 462 m² • Garden/groundskeeper’s house – approx. 100 m² Loan metrics are strong. Even in the current as-is situation, the loan-to-cost level is responsible at 66% LTC, and the borrower provides a personal guarantee. Overall, this represents a responsible financing for RED IV.
A6: ='Loan Tape'!B7 -> 507 | B6: ='Loan Tape'!C7 -> Ridderkerk | C6: ='Loan Tape'!D7 -> Leased | D6: ='Loan Tape'!E7 -> Existing shopping center on ground floor; Refurbishment of vacant upper floors into care apartments | E6: ='Loan Tape'!F7 -> Retail | F6: ='Loan Tape'!G7 -> TRUE | G6: ='Loan Tape'!H7 -> RED IV | H6: ='Loan Tape'!J7 -> 6500000 | I6: ='Loan Tape'!K7 -> 4693871.8 | J6: ='Loan Tape'!L7 -> 1806128.2 | K6: ='Loan Tape'!M7 -> 0.0865 | L6: ='Loan Tape'!O7 -> 45962 | M6: ='Loan Tape'!P7 -> 46478 | N6: ='Loan Tape'!Q7 -> 1369000 | O6: ='Loan Tape'!R7 -> 20460000 | P6: ='Loan Tape'!T7 -> 0.31769306 | Q6: ='Loan Tape'!U7 -> 1.412731 | R6: ='Loan Tape'!V7 -> https://maps.app.goo.gl/8vhTyidXzgWG7xhE7 | S6: ='Loan Tape'!W7 -> https://kadastralekaart.com/kaart/perceel/RDK01/H/6686 | T6: ='Loan Tape'!X7 -> https://i.imgur.com/yuPTY3y.png | U6: ='Loan Tape'!Y7 -> Property, shopping centre, consists of 21 retail units and an underground Q-Park garage (140 spaces). Annual rental income €724.000 (excl. €170.000 service charges), WAULT 8.6 years, with HEMA as anchor tenant. Borrower will convert the former (vacant) library on the first floor into 38 healthcare-residential units (1.180 m²). Permit is irrevocable and all units are pre-leased to one healthcare operator (contract signed). We finance the construction, but we hold the first mortgage right over the entire asset. Low leverage: 32% LTV. Borrower is a reputable and experienced real estate developer. Conclusion: Low-risk loan backed by leased-retail cash flow and a secured, pre-leased healthcare redevelopment.
A7: ='Loan Tape'!B8 -> 509 | B7: ='Loan Tape'!C8 -> Rotterdam | C7: ='Loan Tape'!D8 -> Leased | D7: ='Loan Tape'!E8 -> Leased asset to a medical centre. Possible future redevelopment | E7: ='Loan Tape'!F8 -> Mixed | F7: ='Loan Tape'!G8 -> TRUE | G7: ='Loan Tape'!H8 -> RED IV | H7: ='Loan Tape'!J8 -> 1500000 | I7: ='Loan Tape'!K8 -> 1500000 | J7: ='Loan Tape'!L8 -> 0 | K7: ='Loan Tape'!M8 -> 0.0775 | L7: ='Loan Tape'!O8 -> 45962 | M7: ='Loan Tape'!P8 -> 46486 | N7: ='Loan Tape'!Q8 -> 160000 | O7: ='Loan Tape'!R8 -> 2200000 | P7: ='Loan Tape'!T8 -> 0.68181818 | Q7: ='Loan Tape'!U8 -> 1.4346338 | R7: ='Loan Tape'!V8 -> https://maps.app.goo.gl/FptBuZHcGyUDT5H86 | S7: ='Loan Tape'!W8 -> https://kadastralekaart.com/kaart/perceel/RTD05/Q/4075 | T7: ='Loan Tape'!X8 -> https://i.imgur.com/QE6pVzd.png | U7: ='Loan Tape'!Y8 -> Financing of an office building (leasehold) in Rotterdam – Kop van Zuid. Borrower acquired the asset in 2024 for €2.250.000 (approx. 66% LTC). The property comprises 1.646 m² GFA (incl. 313 m² basement) and 900 m² usable area, across a basement, ground floor, two upper floors and an attic, on a 945 m² plot. The building is fully leased to a large physiotherapy practice for ~€160,000 p.a.. Lease runs until Oct-2031. The property has redevelopment potential. Borrower is progressing a hotel redevelopment plan and permit application, aligned with the municipal area vision. Zoning (“Gemengd – 3”) allows residential, office, commercial, social and hotel/hospitality uses. We finance on the as-is value. Location and future potential enhance marketability. Rental income covers interest (ICR ~1.09) and borrower provides a personal guarantee. Overall, a low-risk financing with secure cash flow, solid collateral and (future) upside from redevelopment. Exit expected via refinancing upon permit approval.
A8: ='Loan Tape'!B9 -> 510 | B8: ='Loan Tape'!C9 -> Muiden | C8: ='Loan Tape'!D9 -> Development | D8: ='Loan Tape'!E9 -> Top-up construction facility for completion of apartment complex | E8: ='Loan Tape'!F9 -> Residential | F8: ='Loan Tape'!G9 -> FALSE | G8: ='Loan Tape'!H9 -> RED IV | H8: ='Loan Tape'!J9 -> 2700000 | I8: ='Loan Tape'!K9 -> 2700000 | J8: ='Loan Tape'!L9 -> 0 | K8: ='Loan Tape'!M9 -> 0.09 | L8: ='Loan Tape'!O9 -> 45931 | M8: ='Loan Tape'!P9 -> 46387 | N8: ='Loan Tape'!Q9 -> 0 | O8: ='Loan Tape'!R9 -> 8000000 | P8: ='Loan Tape'!T9 -> 0.3375 | Q8: ='Loan Tape'!U9 -> 1.24846 | R8: ='Loan Tape'!V9 -> https://maps.app.goo.gl/ZC6GoESnvdcv5QAb9 | S8: ='Loan Tape'!W9 -> https://kadastralekaart.com/kaart/perceel/MDN01/B/2682 | T8: ='Loan Tape'!X9 -> https://i.imgur.com/LkntWiX.png | U8: ='Loan Tape'!Y9 -> Fnancing of the construction of phase 3 of this resi-project (“De Werf bij de Sluis in Muiden”). The construction of phase 2 is almost finished. The project consists of high-end apartments located at the Vecht-river, including a sports-harbour. The borrower is a well-capitalized and professional party with a good track-record in developing. The security comes from the underlying value of the assets which is partly the land position of Phase 3 and the unsold apartments of phase 2. Loan metrics are good. Overall, this is a responsible loan for RED IV.
A9: ='Loan Tape'!B10 -> 511 | B9: ='Loan Tape'!C10 -> Amsterdam | C9: ='Loan Tape'!D10 -> Leased | D9: ='Loan Tape'!E10 -> Short term Bridge finance of leased resi units in Amsterdam | E9: ='Loan Tape'!F10 -> Residential | F9: ='Loan Tape'!G10 -> TRUE | G9: ='Loan Tape'!H10 -> RED IV | H9: ='Loan Tape'!J10 -> 2500000 | I9: ='Loan Tape'!K10 -> 2500000 | J9: ='Loan Tape'!L10 -> 0 | K9: ='Loan Tape'!M10 -> 0.08 | L9: ='Loan Tape'!O10 -> 45962 | M9: ='Loan Tape'!P10 -> 46142 | N9: ='Loan Tape'!Q10 -> 124000 | O9: ='Loan Tape'!R10 -> 5138480 | P9: ='Loan Tape'!T10 -> 0.4865252 | Q9: ='Loan Tape'!U10 -> 0.49281314 | R9: ='Loan Tape'!V10 -> 0 | S9: ='Loan Tape'!W10 -> 0 | T9: ='Loan Tape'!X10 -> 0 | U9: ='Loan Tape'!Y10 -> The company requires temporary liquidity to bridge the period until completion of an ongoing refinancing process with a major bank. Several unencumbered assets are available as collateral, mainly residential units (split apartments) in Amsterdam, generating approximately €124,000 gross per year, complemented by three owner-occupied commercial properties. The total portfolio value, including these assets, amounts to roughly €5.44 million, resulting in an LTV between 46–57%. The facility is provided at a conservative level considering the underlying value of the collateral. The vacant value of the residential assets is significantly higher than the current low rental levels. The portfolio consists of 18 apartments in Amsterdam, two commercial properties in the Western Docklands, two industrial sites in Emmeloord, one apartment in Hilversum, and a recently acquired residential property in Hilversum valued at €1.5 million and situated on 7,100 m² of land. The average loan amount per asset, excluding the Hilversum residence, is around €108,000, with an estimated average value of €235,000. This reflects a prudent financing level given the liquidity and quality of the assets, of which approximately 75% are Amsterdam apartments. The borrower is financially solid with sufficient cash flow and a long-standing profitable track record. Assets are well-located and easily marketable. The operator has extensive experience in real estate and provides personal recourse. Exit will occur through refinancing once the bank facility is completed. Overall, a suitable proposition for RED IV.
A10: ='Loan Tape'!B11 -> 513 | B10: ='Loan Tape'!C11 -> Den Bosch | C10: ='Loan Tape'!D11 -> Leased | D10: ='Loan Tape'!E11 -> Leased, office asset - multi tenants | E10: ='Loan Tape'!F11 -> Office | F10: ='Loan Tape'!G11 -> TRUE | G10: ='Loan Tape'!H11 -> RED IV | H10: ='Loan Tape'!J11 -> 8250000 | I10: ='Loan Tape'!K11 -> 8250000 | J10: ='Loan Tape'!L11 -> 0 | K10: ='Loan Tape'!M11 -> 0.0715 | L10: ='Loan Tape'!O11 -> 46023 | M10: ='Loan Tape'!P11 -> 47105 | N10: ='Loan Tape'!Q11 -> 1230000 | O10: ='Loan Tape'!R11 -> 13800000 | P10: ='Loan Tape'!T11 -> 0.59782609 | Q10: ='Loan Tape'!U11 -> 2.9623546 | R10: ='Loan Tape'!V11 -> https://maps.app.goo.gl/bs2Ne8cMyrQArArX7 | S10: ='Loan Tape'!W11 -> https://kadastralekaart.com/kaart/perceel/HTG00/S/478 | T10: ='Loan Tape'!X11 -> https://i.imgur.com/Re0YyXC.png | U10: ='Loan Tape'!Y11 -> This financing concerns the acquisition of a fully leased office property in ’s-Hertogenbosch. The asset consists of three connected towers with a flexible layout, allowing for separation into individual units, and provides approximately 6,300m² LFA with ample parking. The property is modern, recently renovated, energy efficient and generates stable rental income.The WALT of 4.97 years strengthens the income profile, while a €1 million cash-sweep mechanism further mitigates risk by directly linking our exposure to rental performance. Exit risk is limited; supported by strong occupancy (WALT) and a long-term redevelopment potential into healthcare housing as a future upside alternative. While such redevelopment would require substantial work and time — zoning changes and permits — it provides an attractive optionality. Even if redevelopment proves challenging, the property in its current state remains a well-lettable investment product with solid saleability, particularly at the applied financing level.
A11: ='Loan Tape'!B12 -> 514 | B11: ='Loan Tape'!C12 -> Amsterdam | C11: ='Loan Tape'!D12 -> Leased | D11: ='Loan Tape'!E12 -> Resi asset with plan to split into smaller units and sale | E11: ='Loan Tape'!F12 -> Residential | F11: ='Loan Tape'!G12 -> FALSE | G11: ='Loan Tape'!H12 -> RED IV | H11: ='Loan Tape'!J12 -> 700000 | I11: ='Loan Tape'!K12 -> 700000 | J11: ='Loan Tape'!L12 -> 0 | K11: ='Loan Tape'!M12 -> 0.0825 | L11: ='Loan Tape'!O12 -> 45962 | M11: ='Loan Tape'!P12 -> 46507 | N11: ='Loan Tape'!Q12 -> 47000 | O11: ='Loan Tape'!R12 -> 960000 | P11: ='Loan Tape'!T12 -> 0.72916667 | Q11: ='Loan Tape'!U12 -> 1.4921287 | R11: ='Loan Tape'!V12 -> https://maps.app.goo.gl/hAtL4DG9LciUpMXdA | S11: ='Loan Tape'!W12 -> https://kadastralekaart.com/kaart/perceel/ASD07/K/8669 | T11: ='Loan Tape'!X12 -> https://i.imgur.com/KmOoASF.jpeg | U11: ='Loan Tape'!Y12 -> This financing concerns the acquisition of a leased residential property in Amsterdam-Noord (leasehold) consisting of three units with a total GFA of roughly 250–275m². The borrower intends to vacate the units, legally subdivide the property and either sell the apartments individually or renovate further depending on market conditions. The valuation supports the business plan, with current value around €960.000 and exit potential of €1.500.000–€1.650.000. Key risks relate to liquidity pressure and timing of subdivision, mitigated by an 18-month interest reserve and personal guarantees. Overall, the loan amount is considered acceptable given the vacant-possession potential and marketability.
A12: ='Loan Tape'!B13 -> 515 | B12: ='Loan Tape'!C13 -> Utrecht | C12: ='Loan Tape'!D13 -> Leased | D12: ='Loan Tape'!E13 -> Multi tenant offices. Possible long term redevelopment potential | E12: ='Loan Tape'!F13 -> Office | F12: ='Loan Tape'!G13 -> TRUE | G12: ='Loan Tape'!H13 -> RED IV | H12: ='Loan Tape'!J13 -> 12000000 | I12: ='Loan Tape'!K13 -> 12000000 | J12: ='Loan Tape'!L13 -> 0 | K12: ='Loan Tape'!M13 -> 0.07 | L12: ='Loan Tape'!O13 -> 46054 | M12: ='Loan Tape'!P13 -> 47114 | N12: ='Loan Tape'!Q13 -> 2150000 | O12: ='Loan Tape'!R13 -> 20050000 | P12: ='Loan Tape'!T13 -> 0.59850374 | Q12: ='Loan Tape'!U13 -> 2.9021218 | R12: ='Loan Tape'!V13 -> https://maps.app.goo.gl/6aTGsroijrGwSurw7 | S12: ='Loan Tape'!W13 -> https://kadastralekaart.com/kaart/perceel/UTT00/O/1117 | T12: ='Loan Tape'!X13 -> https://i.imgur.com/xljbU1O.png | U12: ='Loan Tape'!Y13 -> This proposal concerns the financing of multiple commercial objects located near the FC Utrecht stadium. In the near future, there are opportunities to redevelop the area, with the possibility to add residential units on top of the existing structures. Borrower wishes to bridge the term to obtain a permit for this redevelopment. Borrower is an SPV with two sponsors: a professional developer with proven track-record and a private investor with healthy financials. There is only limited recourse. Objects are well-maintained and well-rented to cover the interest expenses. WALT is acceptable given the maturity of this loan. LTV based on the as is situation and cash flow are sufficient. The loan is fits well within the terms of RED.
A13: ='Loan Tape'!B14 -> 518 | B13: ='Loan Tape'!C14 -> Amsterdam / Almere / Amersfoort | C13: ='Loan Tape'!D14 -> Leased | D13: ='Loan Tape'!E14 -> Portfolio of residential, commercial and office assets | E13: ='Loan Tape'!F14 -> Mixed | F13: ='Loan Tape'!G14 -> TRUE | G13: ='Loan Tape'!H14 -> TLFJANA | H13: ='Loan Tape'!J14 -> 5000000 | I13: ='Loan Tape'!K14 -> 5000000 | J13: ='Loan Tape'!L14 -> 0 | K13: ='Loan Tape'!M14 -> 0.09 | L13: ='Loan Tape'!O14 -> 46054 | M13: ='Loan Tape'!P14 -> 46215 | N13: ='Loan Tape'!Q14 -> 867000 | O13: ='Loan Tape'!R14 -> 14580000 | P13: ='Loan Tape'!T14 -> 0.34293553 | Q13: ='Loan Tape'!U14 -> 0.44079398 | R13: ='Loan Tape'!V14 -> 0 | S13: ='Loan Tape'!W14 -> 0 | T13: ='Loan Tape'!X14 -> 0 | U13: ='Loan Tape'!Y14 -> 0
... A15: ='Loan Tape'!B16 -> 522 | B15: ='Loan Tape'!C16 -> Zevenaar | C15: ='Loan Tape'!D16 -> Development | D15: ='Loan Tape'!E16 -> Fully permitted land for residential development | E15: ='Loan Tape'!F16 -> Residential | F15: ='Loan Tape'!G16 -> FALSE | G15: ='Loan Tape'!H16 -> RED IV | H15: ='Loan Tape'!J16 -> 3000000 | I15: ='Loan Tape'!K16 -> 3000000 | J15: ='Loan Tape'!L16 -> 0 | K15: ='Loan Tape'!M16 -> 0.083 | L15: ='Loan Tape'!O16 -> 46054 | M15: ='Loan Tape'!P16 -> 46589 | N15: ='Loan Tape'!Q16 -> 0 | O15: ='Loan Tape'!R16 -> 10000000 | P15: ='Loan Tape'!T16 -> 0.3 | Q15: ='Loan Tape'!U16 -> 1.4647502 | R15: ='Loan Tape'!V16 -> 0 | S15: ='Loan Tape'!W16 -> 0 | T15: ='Loan Tape'!X16 -> 0 | U15: ='Loan Tape'!Y16 -> 0

Sheet mutations
A1: TMO New | J1: TMO Old | Q1: Delta
A2: Account | B2: Principal Balance | C2: Original Balance | D2: Maturity Date | E2: Appraisal Date | F2: Aggregate Appraised Value | G2: Note Rate | H2: Change | I2: Account.1 | J2: Principal Balance.1 | K2: Original Balance.1 | L2: Maturity Date.1 | M2: Appraisal Date.1 | N2: Aggregate Appraised Value.1 | O2: Note Rate.1 | Q2: =Merge1[[#Headers],[Account]] -> Account | R2: =Merge1[[#Headers],[Principal Balance]] -> Principal Balance | S2: =Merge1[[#Headers],[Original Balance]] -> Original Balance | T2: =Merge1[[#Headers],[Maturity Date]] -> Maturity Date | U2: =Merge1[[#Headers],[Appraisal Date]] -> Appraisal Date | V2: =Merge1[[#Headers],[Aggregate Appraised Value]] -> Aggregate Appraised Value | W2: =Merge1[[#Headers],[Note Rate]] -> Note Rate
A3: 484 | B3: 8696509.1 | C3: 25000000 | D3: 46692 | E3: 45741 | F3: 39300000 | G3: 0.08 | H3: Changed | I3: 484 | J3: 8625361.2 | K3: 25000000 | L3: 46692 | M3: 45741 | N3: 39300000 | O3: 0.08 | Q3: =IF(Merge1[[#This Row],[Account]]=0,Merge1[[#This Row],[Account.1]],Merge1[[#This Row],[Account]]) -> 484 | R3: =-Merge1[[#This Row],[Principal Balance.1]]+Merge1[[#This Row],[Principal Balance]] -> 71147.94 | S3: =-Merge1[[#This Row],[Original Balance.1]]+Merge1[[#This Row],[Original Balance]] -> 0 | T3: =IF(Merge1[[#This Row],[Maturity Date.1]]-Merge1[[#This Row],[Maturity Date]]=0,"",Merge1[[#This Row],[Maturity Date]]) | U3: =IF(Merge1[[#This Row],[Appraisal Date.1]]-Merge1[[#This Row],[Appraisal Date]]=0,"",Merge1[[#This Row],[Appraisal Date]]) | V3: =Merge1[[#This Row],[Aggregate Appraised Value.1]]-Merge1[[#This Row],[Aggregate Appraised Value]] -> 0 | W3: =Merge1[[#This Row],[Note Rate.1]]-Merge1[[#This Row],[Note Rate]] -> 0
A4: 507 | B4: 4177117 | C4: 6500000 | D4: 46478 | E4: 45820 | F4: 20460000 | G4: 0.0865 | H4: Changed | I4: 507 | J4: 3918742.1 | K4: 6500000 | L4: 46478 | M4: 45820 | N4: 20460000 | O4: 0.0865 | Q4: =IF(Merge1[[#This Row],[Account]]=0,Merge1[[#This Row],[Account.1]],Merge1[[#This Row],[Account]]) -> 507 | R4: =-Merge1[[#This Row],[Principal Balance.1]]+Merge1[[#This Row],[Principal Balance]] -> 258374.93 | S4: =-Merge1[[#This Row],[Original Balance.1]]+Merge1[[#This Row],[Original Balance]] -> 0 | T4: =IF(Merge1[[#This Row],[Maturity Date.1]]-Merge1[[#This Row],[Maturity Date]]=0,"",Merge1[[#This Row],[Maturity Date]]) | U4: =IF(Merge1[[#This Row],[Appraisal Date.1]]-Merge1[[#This Row],[Appraisal Date]]=0,"",Merge1[[#This Row],[Appraisal Date]]) | V4: =Merge1[[#This Row],[Aggregate Appraised Value.1]]-Merge1[[#This Row],[Aggregate Appraised Value]] -> 0 | W4: =Merge1[[#This Row],[Note Rate.1]]-Merge1[[#This Row],[Note Rate]] -> 0
A5: 518 | B5: 5000000 | C5: 5000000 | D5: 46215 | E5: 46023 | F5: 14580000 | G5: 0.09 | H5: Added | Q5: =IF(Merge1[[#This Row],[Account]]=0,Merge1[[#This Row],[Account.1]],Merge1[[#This Row],[Account]]) -> 518 | R5: =-Merge1[[#This Row],[Principal Balance.1]]+Merge1[[#This Row],[Principal Balance]] -> 5000000 | S5: =-Merge1[[#This Row],[Original Balance.1]]+Merge1[[#This Row],[Original Balance]] -> 5000000 | T5: =IF(Merge1[[#This Row],[Maturity Date.1]]-Merge1[[#This Row],[Maturity Date]]=0,"",Merge1[[#This Row],[Maturity Date]]) -> 46215 | U5: =IF(Merge1[[#This Row],[Appraisal Date.1]]-Merge1[[#This Row],[Appraisal Date]]=0,"",Merge1[[#This Row],[Appraisal Date]]) -> 46023 | V5: =Merge1[[#This Row],[Aggregate Appraised Value.1]]-Merge1[[#This Row],[Aggregate Appraised Value]] -> -14580000 | W5: =Merge1[[#This Row],[Note Rate.1]]-Merge1[[#This Row],[Note Rate]] -> -0.09
A6: 522 | B6: 3000000 | C6: 3000000 | D6: 46589 | E6: 46023 | F6: 10000000 | G6: 0.083 | H6: Added | Q6: =IF(Merge1[[#This Row],[Account]]=0,Merge1[[#This Row],[Account.1]],Merge1[[#This Row],[Account]]) -> 522 | R6: =-Merge1[[#This Row],[Principal Balance.1]]+Merge1[[#This Row],[Principal Balance]] -> 3000000 | S6: =-Merge1[[#This Row],[Original Balance.1]]+Merge1[[#This Row],[Original Balance]] -> 3000000 | T6: =IF(Merge1[[#This Row],[Maturity Date.1]]-Merge1[[#This Row],[Maturity Date]]=0,"",Merge1[[#This Row],[Maturity Date]]) -> 46589 | U6: =IF(Merge1[[#This Row],[Appraisal Date.1]]-Merge1[[#This Row],[Appraisal Date]]=0,"",Merge1[[#This Row],[Appraisal Date]]) -> 46023 | V6: =Merge1[[#This Row],[Aggregate Appraised Value.1]]-Merge1[[#This Row],[Aggregate Appraised Value]] -> -10000000 | W6: =Merge1[[#This Row],[Note Rate.1]]-Merge1[[#This Row],[Note Rate]] -> -0.083
